MANIFEST.in
README.rst
setup.cfg
setup.py
collective/__init__.py
collective.externalizelink.egg-info/PKG-INFO
collective.externalizelink.egg-info/SOURCES.txt
collective.externalizelink.egg-info/dependency_links.txt
collective.externalizelink.egg-info/entry_points.txt
collective.externalizelink.egg-info/namespace_packages.txt
collective.externalizelink.egg-info/not-zip-safe
collective.externalizelink.egg-info/requires.txt
collective.externalizelink.egg-info/top_level.txt
collective/externalizelink/__init__.py
collective/externalizelink/configuration.py
collective/externalizelink/configure.zcml
collective/externalizelink/controlpanel.pt
collective/externalizelink/controlpanel.py
collective/externalizelink/i18n.pt
collective/externalizelink/interfaces.py
collective/externalizelink/persistent_field.py
collective/externalizelink/testing.py
collective/externalizelink/Extensions/install.py
collective/externalizelink/locales/collective.externalizelink-manual.pot
collective/externalizelink/locales/collective.externalizelink.pot
collective/externalizelink/locales/rebuildPo.sh
collective/externalizelink/locales/it/LC_MESSAGES/collective.externalizelink.mo
collective/externalizelink/locales/it/LC_MESSAGES/collective.externalizelink.po
collective/externalizelink/profiles/default/browserlayer.xml
collective/externalizelink/profiles/default/controlpanel.xml
collective/externalizelink/profiles/default/jsregistry.xml
collective/externalizelink/profiles/default/metadata.xml
collective/externalizelink/profiles/default/registry.xml
collective/externalizelink/profiles/uninstall/browserlayer.xml
collective/externalizelink/profiles/uninstall/controlpanel.xml
collective/externalizelink/profiles/uninstall/jsregistry.xml
collective/externalizelink/profiles/uninstall/registry.xml
collective/externalizelink/resources/external.png
collective/externalizelink/resources/externalize-links.js
docs/HISTORY.rst
docs/INSTALL.txt
docs/LICENSE.GPL
docs/LICENSE.txt