Metadata-Version: 1.1
Name: collective.externalizelink
Version: 0.1.0
Summary: Controls when Plone must open links in external page (in an accessible way)
Home-page: https://github.com/keul/collective.externalizelink
Author: keul
Author-email: luca@keul.it
License: GPL
Keywords: plone link popup open
Platform: UNKNOWN
Classifier: Framework :: Plone
Classifier: Framework :: Plone :: 4.3
Classifier: Programming Language :: Python
Classifier: Programming Language :: JavaScript
Classifier: License :: OSI Approved :: GNU General Public License (GPL)
